{
  "users": [
      {
        "id":1,
        "isActive":false,
        "age":49,
        "name":"Juliana Gottlieb II",
        "gender":"Male",
        "company":"Herzog Inc",
        "email":"clothing@domain.com",
        "phone":"020-272-2395-86576",
        "address":"7580 DuBuque Centers, New Vanessa, IN 07536"
      },
      {
        "id":2,
        "isActive":true,
        "age":56,
        "name":"Ms. Delores O\u0027Keefe",
        "gender":"Female",
        "company":"Will-Koss",
        "email":"outdoors@domain.com",
        "phone":"150-704-6933-3849",
        "address":"Suite 427 645 Dietrich Flat, Lake Lilliam, AK 95720"
      },
      {
        "id":3,
        "isActive":false,
        "age":29,
        "name":"Pia Kshlerin",
        "gender":"Male",
        "company":"Wolf LLC",
        "email":"electronics@domain.com",
        "phone":"1-725-636-7163-032",
        "address":"Apt. 297 00639 Shelby Rapid, Haleyberg, WY 31343-5468"
      },
      {
        "id":4,
        "isActive":false,
        "age":53,
        "name":"Dee Hintz",
        "gender":"Female",
        "company":"Larkin Inc",
        "email":"home@domain.com",
        "phone":"1-142-556-0587-549",
        "address":"Suite 761 616 Ortiz Prairie, Lake Freddaland, IA 06274"
      },
      {
        "id":5,
        "isActive":true,
        "age":40,
        "name":"Bea Jast",
        "gender":"Female",
        "company":"D\u0027Amore Group",
        "email":"beauty@domain.com",
        "phone":"101.086.6372-56354",
        "address":"11428 Kozey Ferry, New Davis, MN 15363"
      },
      {
        "id":6,
        "isActive":false,
        "age":60,
        "name":"Natacha Wuckert",
        "gender":"Male",
        "company":"O\u0027Reilly-Donnelly",
        "email":"industrial@domain.com",
        "phone":"(418)393-3017-850",
        "address":"Suite 201 1734 Mohr Fields, Edaburgh, MN 50015"
      },
      {
        "id":7,
        "isActive":true,
        "age":59,
        "name":"Otha Klein",
        "gender":"Female",
        "company":"Jones, Will and O\u0027Kon",
        "email":"grocery@domain.com",
        "phone":"645.296.0790-014",
        "address":"Suite 986 764 Adan Roads, East Marlon, MT 97865"
      },
      {
        "id":8,
        "isActive":true,
        "age":61,
        "name":"Brain Lehner",
        "gender":"Male",
        "company":"Labadie-Bernier",
        "email":"movies@domain.com",
        "phone":"715-678-2011-4508",
        "address":"Apt. 853 9130 Daria Rapids, New Ervin, NE 43547-6554"
      },
      {
        "id":9,
        "isActive":true,
        "age":43,
        "name":"Jama Armstrong",
        "gender":"Male",
        "company":"Cremin and Sons",
        "email":"clothing@domain.com",
        "phone":"847-771-5223-436",
        "address":"Suite 584 94025 Dona Parks, Miltonport, NM 51843-5969"
      },
      {
        "id":10,
        "isActive":false,
        "age":40,
        "name":"Theron Rippin",
        "gender":"Female",
        "company":"Swift-Tremblay",
        "email":"beauty@domain.com",
        "phone":"668.197.6903-435",
        "address":"981 Effertz Fort, New Rolanda, SC 70526-2464"
      },
      {
        "id":11,
        "isActive":false,
        "age":52,
        "name":"Duane Yundt",
        "gender":"Female",
        "company":"Herzog Inc",
        "email":"beauty@domain.com",
        "phone":"640-835-0340-218",
        "address":"6774 Bogan Extensions, Fishertown, NJ 75230"
      },
      {
        "id":12,
        "isActive":true,
        "age":54,
        "name":"Cesar Dach DVM",
        "gender":"Female",
        "company":"Littel, Bode and Haley",
        "email":"computers@domain.com",
        "phone":"(061)779-0804-1790",
        "address":"Suite 493 7888 Bradtke Via, Jenkinsfort, DE 97956-6199"
      },
      {
        "id":13,
        "isActive":true,
        "age":29,
        "name":"Terrance Grimes III",
        "gender":"Male",
        "company":"Howe, Gleason and Goldner",
        "email":"computers@domain.com",
        "phone":"1-263-598-3648",
        "address":"Apt. 543 3839 Mann Heights, New Wallacemouth, AL 67121-7540"
      },
      {
        "id":14,
        "isActive":false,
        "age":47,
        "name":"Demetrius Smitham",
        "gender":"Female",
        "company":"Beer Group",
        "email":"baby@domain.com",
        "phone":"1-776-898-7868-11916",
        "address":"9070 Milan Pine, Lesterland, WI 00706-1635"
      },
      {
        "id":15,
        "isActive":true,
        "age":54,
        "name":"Chloe Reynolds Jr.",
        "gender":"Female",
        "company":"Jacobs LLC",
        "email":"computers@domain.com",
        "phone":"1-756-147-4687-965",
        "address":"Suite 457 34444 Peter Overpass, North Alvin, ND 89749-3007"
      },
      {
        "id":16,
        "isActive":false,
        "age":25,
        "name":"Terrance Bernier",
        "gender":"Female",
        "company":"Schamberger and Sons",
        "email":"toys@domain.com",
        "phone":"(362)460-1334-66792",
        "address":"4155 Jacob Green, Kristinashire, SD 88637"
      },
      {
        "id":17,
        "isActive":true,
        "age":44,
        "name":"Eduardo Halvorson",
        "gender":"Female",
        "company":"Keeling Group",
        "email":"movies@domain.com",
        "phone":"(300)199-5426-4741",
        "address":"Suite 360 57683 Spencer Mall, Schowalterfort, IN 36309"
      },
      {
        "id":18,
        "isActive":true,
        "age":40,
        "name":"Tisa Kozey",
        "gender":"Female",
        "company":"Gorczany, Tremblay and Cummerata",
        "email":"toys@domain.com",
        "phone":"(725)005-3697-741",
        "address":"Apt. 893 18346 Nienow Haven, Hilaryborough, KS 74592"
      },
      {
        "id":19,
        "isActive":true,
        "age":33,
        "name":"Avery Ullrich",
        "gender":"Male",
        "company":"Weber and Sons",
        "email":"tools@domain.com",
        "phone":"884.417.2175-497",
        "address":"Apt. 312 571 Boyer Ramp, Port Jaimeland, OR 39927"
      },
      {
        "id":20,
        "isActive":false,
        "age":52,
        "name":"Yasmin Satterfield",
        "gender":"Male",
        "company":"Steuber-Russel",
        "email":"health@domain.com",
        "phone":"170-335-0712",
        "address":"Suite 539 43985 Cruickshank Springs, Kleinmouth, PA 06961"
      },
      {
        "id":21,
        "isActive":true,
        "age":39,
        "name":"Chuck Senger",
        "gender":"Male",
        "company":"Ratke, Mueller and Fadel",
        "email":"beauty@domain.com",
        "phone":"(625)103-5176",
        "address":"353 Collier Rapid, Randallburgh, SD 84446"
      },
      {
        "id":22,
        "isActive":false,
        "age":51,
        "name":"Cristobal Walsh II",
        "gender":"Male",
        "company":"Kreiger, Gottlieb and Robel",
        "email":"toys@domain.com",
        "phone":"(978)196-1299",
        "address":"Suite 856 19867 Bogisich Orchard, South Frederick, UT 32764"
      },
      {
        "id":23,
        "isActive":true,
        "age":61,
        "name":"Diego Koepp",
        "gender":"Male",
        "company":"Tillman, Trantow and Leffler",
        "email":"games@domain.com",
        "phone":"1-700-054-1108-969",
        "address":"5790 Kuhic Circle, East Reathafort, NC 64338"
      },
      {
        "id":24,
        "isActive":true,
        "age":33,
        "name":"Charles Bruen",
        "gender":"Female",
        "company":"Schiller LLC",
        "email":"books@domain.com",
        "phone":"190-829-7066-466",
        "address":"Apt. 010 8432 Wes Glens, East Tamera, TN 91987-6684"
      },
      {
        "id":25,
        "isActive":true,
        "age":43,
        "name":"Alexis Hane",
        "gender":"Female",
        "company":"Kutch Inc",
        "email":"outdoors@domain.com",
        "phone":"635-802-1082",
        "address":"Suite 831 0816 Wiegand Light, Lake Eliseotown, MN 30259-3256"
      },
      {
        "id":26,
        "isActive":false,
        "age":39,
        "name":"Ronald Gusikowski",
        "gender":"Male",
        "company":"Gutkowski-Upton",
        "email":"baby@domain.com",
        "phone":"671-056-9101-947",
        "address":"Suite 222 309 Kit Ford, West Patfort, NV 07648-1531"
      },
      {
        "id":27,
        "isActive":false,
        "age":64,
        "name":"Meg Lang",
        "gender":"Male",
        "company":"Waters, Skiles and Stanton",
        "email":"outdoors@domain.com",
        "phone":"864.266.5638-89555",
        "address":"Suite 694 990 Bergnaum Passage, O\u0027Haraview, TX 61581-2252"
      },
      {
        "id":28,
        "isActive":true,
        "age":48,
        "name":"Markus Crooks",
        "gender":"Male",
        "company":"Metz-Bartoletti",
        "email":"music@domain.com",
        "phone":"392.783.3920",
        "address":"Suite 623 82026 Rex Passage, Ofeliamouth, KS 41438-8118"
      },
      {
        "id":29,
        "isActive":false,
        "age":34,
        "name":"Thanh Krajcik",
        "gender":"Female",
        "company":"Braun, Connelly and Gaylord",
        "email":"industrial@domain.com",
        "phone":"015.895.7529-47939",
        "address":"Suite 575 104 Cruz Drives, Armandoland, KS 22616"
      },
      {
        "id":30,
        "isActive":true,
        "age":56,
        "name":"Morgan Emmerich",
        "gender":"Male",
        "company":"Kohler, Hackett and Prosacco",
        "email":"home@domain.com",
        "phone":"242.670.2740-966",
        "address":"Apt. 210 705 Hiroko Park, West Zolabury, MD 58279-4747"
      }
    ]
}
